{
  "openapi": "3.0.1",
  "info": {
    "title": "Bus_ticketing_Backend",
    "version": "1.0"
  },
  "paths": {
    "/api/Booking": {
      "get": {
        "tags": [
          "Booking"
        ],
        "responses": {
          "200": {
            "description": "OK",
            "content": {
              "text/plain": {
                "schema": {
                  "type": "array",
                  "items": {
                    "$ref": "#/components/schemas/BookingDto"
                  }
                }
              },
              "application/json": {
                "schema": {
                  "type": "array",
                  "items": {
                    "$ref": "#/components/schemas/BookingDto"
                  }
                }
              },
              "text/json": {
                "schema": {
                  "type": "array",
                  "items": {
                    "$ref": "#/components/schemas/BookingDto"
                  }
                }
              }
            }
          }
        }
      },
      "post": {
        "tags": [
          "Booking"
        ],
        "requestBody": {
          "content": {
            "application/json": {
              "schema": {
                "$ref": "#/components/schemas/CreateBookingDto"
              }
            },
            "text/json": {
              "schema": {
                "$ref": "#/components/schemas/CreateBookingDto"
              }
            },
            "application/*+json": {
              "schema": {
                "$ref": "#/components/schemas/CreateBookingDto"
              }
            }
          }
        },
        "responses": {
          "200": {
            "description": "OK",
            "content": {
              "text/plain": {
                "schema": {
                  "$ref": "#/components/schemas/BookingDto"
                }
              },
              "application/json": {
                "schema": {
                  "$ref": "#/components/schemas/BookingDto"
                }
              },
              "text/json": {
                "schema": {
                  "$ref": "#/components/schemas/BookingDto"
                }
              }
            }
          }
        }
      }
    },
    "/api/Booking/my-bookings": {
      "get": {
        "tags": [
          "Booking"
        ],
        "responses": {
          "200": {
            "description": "OK",
            "content": {
              "text/plain": {
                "schema": {
                  "type": "array",
                  "items": {
                    "$ref": "#/components/schemas/BookingDto"
                  }
                }
              },
              "application/json": {
                "schema": {
                  "type": "array",
                  "items": {
                    "$ref": "#/components/schemas/BookingDto"
                  }
                }
              },
              "text/json": {
                "schema": {
                  "type": "array",
                  "items": {
                    "$ref": "#/components/schemas/BookingDto"
                  }
                }
              }
            }
          }
        }
      }
    },
    "/api/Booking/{id}": {
      "get": {
        "tags": [
          "Booking"
        ],
        "parameters": [
          {
            "name": "id",
            "in": "path",
            "required": true,
            "schema": {
              "type": "string",
              "format": "uuid"
            }
          }
        ],
        "responses": {
          "200": {
            "description": "OK",
            "content": {
              "text/plain": {
                "schema": {
                  "$ref": "#/components/schemas/BookingDto"
                }
              },
              "application/json": {
                "schema": {
                  "$ref": "#/components/schemas/BookingDto"
                }
              },
              "text/json": {
                "schema": {
                  "$ref": "#/components/schemas/BookingDto"
                }
              }
            }
          }
        }
      },
      "delete": {
        "tags": [
          "Booking"
        ],
        "parameters": [
          {
            "name": "id",
            "in": "path",
            "required": true,
            "schema": {
              "type": "string",
              "format": "uuid"
            }
          }
        ],
        "responses": {
          "200": {
            "description": "OK"
          }
        }
      }
    },
    "/api/Bus": {
      "get": {
        "tags": [
          "Bus"
        ],
        "responses": {
          "200": {
            "description": "OK",
            "content": {
              "text/plain": {
                "schema": {
                  "type": "array",
                  "items": {
                    "$ref": "#/components/schemas/BusDto"
                  }
                }
              },
              "application/json": {
                "schema": {
                  "type": "array",
                  "items": {
                    "$ref": "#/components/schemas/BusDto"
                  }
                }
              },
              "text/json": {
                "schema": {
                  "type": "array",
                  "items": {
                    "$ref": "#/components/schemas/BusDto"
                  }
                }
              }
            }
          }
        }
      },
      "post": {
        "tags": [
          "Bus"
        ],
        "requestBody": {
          "content": {
            "application/json": {
              "schema": {
                "$ref": "#/components/schemas/CreateBusDto"
              }
            },
            "text/json": {
              "schema": {
                "$ref": "#/components/schemas/CreateBusDto"
              }
            },
            "application/*+json": {
              "schema": {
                "$ref": "#/components/schemas/CreateBusDto"
              }
            }
          }
        },
        "responses": {
          "200": {
            "description": "OK"
          }
        }
      }
    },
    "/api/Bus/{id}": {
      "get": {
        "tags": [
          "Bus"
        ],
        "parameters": [
          {
            "name": "id",
            "in": "path",
            "required": true,
            "schema": {
              "type": "string",
              "format": "uuid"
            }
          }
        ],
        "responses": {
          "200": {
            "description": "OK",
            "content": {
              "text/plain": {
                "schema": {
                  "$ref": "#/components/schemas/BusDto"
                }
              },
              "application/json": {
                "schema": {
                  "$ref": "#/components/schemas/BusDto"
                }
              },
              "text/json": {
                "schema": {
                  "$ref": "#/components/schemas/BusDto"
                }
              }
            }
          }
        }
      },
      "put": {
        "tags": [
          "Bus"
        ],
        "parameters": [
          {
            "name": "id",
            "in": "path",
            "required": true,
            "schema": {
              "type": "string",
              "format": "uuid"
            }
          }
        ],
        "requestBody": {
          "content": {
            "application/json": {
              "schema": {
                "$ref": "#/components/schemas/UpdateBusDto"
              }
            },
            "text/json": {
              "schema": {
                "$ref": "#/components/schemas/UpdateBusDto"
              }
            },
            "application/*+json": {
              "schema": {
                "$ref": "#/components/schemas/UpdateBusDto"
              }
            }
          }
        },
        "responses": {
          "200": {
            "description": "OK"
          }
        }
      },
      "delete": {
        "tags": [
          "Bus"
        ],
        "parameters": [
          {
            "name": "id",
            "in": "path",
            "required": true,
            "schema": {
              "type": "string",
              "format": "uuid"
            }
          }
        ],
        "responses": {
          "200": {
            "description": "OK"
          }
        }
      }
    },
    "/api/City": {
      "get": {
        "tags": [
          "City"
        ],
        "responses": {
          "200": {
            "description": "OK",
            "content": {
              "text/plain": {
                "schema": {
                  "type": "array",
                  "items": {
                    "$ref": "#/components/schemas/CityDto"
                  }
                }
              },
              "application/json": {
                "schema": {
                  "type": "array",
                  "items": {
                    "$ref": "#/components/schemas/CityDto"
                  }
                }
              },
              "text/json": {
                "schema": {
                  "type": "array",
                  "items": {
                    "$ref": "#/components/schemas/CityDto"
                  }
                }
              }
            }
          }
        }
      }
    },
    "/api/City/{id}": {
      "get": {
        "tags": [
          "City"
        ],
        "parameters": [
          {
            "name": "id",
            "in": "path",
            "required": true,
            "schema": {
              "type": "string"
            }
          }
        ],
        "responses": {
          "200": {
            "description": "OK",
            "content": {
              "text/plain": {
                "schema": {
                  "$ref": "#/components/schemas/CityDto"
                }
              },
              "application/json": {
                "schema": {
                  "$ref": "#/components/schemas/CityDto"
                }
              },
              "text/json": {
                "schema": {
                  "$ref": "#/components/schemas/CityDto"
                }
              }
            }
          }
        }
      }
    },
    "/api/Routes": {
      "get": {
        "tags": [
          "Routes"
        ],
        "responses": {
          "200": {
            "description": "OK",
            "content": {
              "text/plain": {
                "schema": {
                  "type": "array",
                  "items": {
                    "$ref": "#/components/schemas/RouteDto"
                  }
                }
              },
              "application/json": {
                "schema": {
                  "type": "array",
                  "items": {
                    "$ref": "#/components/schemas/RouteDto"
                  }
                }
              },
              "text/json": {
                "schema": {
                  "type": "array",
                  "items": {
                    "$ref": "#/components/schemas/RouteDto"
                  }
                }
              }
            }
          }
        }
      }
    },
    "/api/Routes/{id}": {
      "get": {
        "tags": [
          "Routes"
        ],
        "parameters": [
          {
            "name": "id",
            "in": "path",
            "required": true,
            "schema": {
              "type": "string",
              "format": "uuid"
            }
          }
        ],
        "responses": {
          "200": {
            "description": "OK",
            "content": {
              "text/plain": {
                "schema": {
                  "$ref": "#/components/schemas/RouteDto"
                }
              },
              "application/json": {
                "schema": {
                  "$ref": "#/components/schemas/RouteDto"
                }
              },
              "text/json": {
                "schema": {
                  "$ref": "#/components/schemas/RouteDto"
                }
              }
            }
          }
        }
      }
    },
    "/api/Station": {
      "get": {
        "tags": [
          "Station"
        ],
        "responses": {
          "200": {
            "description": "OK",
            "content": {
              "text/plain": {
                "schema": {
                  "type": "array",
                  "items": {
                    "$ref": "#/components/schemas/StationDto"
                  }
                }
              },
              "application/json": {
                "schema": {
                  "type": "array",
                  "items": {
                    "$ref": "#/components/schemas/StationDto"
                  }
                }
              },
              "text/json": {
                "schema": {
                  "type": "array",
                  "items": {
                    "$ref": "#/components/schemas/StationDto"
                  }
                }
              }
            }
          }
        }
      },
      "post": {
        "tags": [
          "Station"
        ],
        "requestBody": {
          "content": {
            "application/json": {
              "schema": {
                "$ref": "#/components/schemas/CreateStationDto"
              }
            },
            "text/json": {
              "schema": {
                "$ref": "#/components/schemas/CreateStationDto"
              }
            },
            "application/*+json": {
              "schema": {
                "$ref": "#/components/schemas/CreateStationDto"
              }
            }
          }
        },
        "responses": {
          "200": {
            "description": "OK"
          }
        }
      }
    },
    "/api/Station/{id}": {
      "get": {
        "tags": [
          "Station"
        ],
        "parameters": [
          {
            "name": "id",
            "in": "path",
            "required": true,
            "schema": {
              "type": "string",
              "format": "uuid"
            }
          }
        ],
        "responses": {
          "200": {
            "description": "OK",
            "content": {
              "text/plain": {
                "schema": {
                  "$ref": "#/components/schemas/StationDto"
                }
              },
              "application/json": {
                "schema": {
                  "$ref": "#/components/schemas/StationDto"
                }
              },
              "text/json": {
                "schema": {
                  "$ref": "#/components/schemas/StationDto"
                }
              }
            }
          }
        }
      },
      "put": {
        "tags": [
          "Station"
        ],
        "parameters": [
          {
            "name": "id",
            "in": "path",
            "required": true,
            "schema": {
              "type": "string",
              "format": "uuid"
            }
          }
        ],
        "requestBody": {
          "content": {
            "application/json": {
              "schema": {
                "$ref": "#/components/schemas/UpdateStationDto"
              }
            },
            "text/json": {
              "schema": {
                "$ref": "#/components/schemas/UpdateStationDto"
              }
            },
            "application/*+json": {
              "schema": {
                "$ref": "#/components/schemas/UpdateStationDto"
              }
            }
          }
        },
        "responses": {
          "200": {
            "description": "OK"
          }
        }
      },
      "delete": {
        "tags": [
          "Station"
        ],
        "parameters": [
          {
            "name": "id",
            "in": "path",
            "required": true,
            "schema": {
              "type": "string",
              "format": "uuid"
            }
          }
        ],
        "responses": {
          "200": {
            "description": "OK"
          }
        }
      }
    },
    "/api/Trip/search": {
      "get": {
        "tags": [
          "Trip"
        ],
        "parameters": [
          {
            "name": "from",
            "in": "query",
            "schema": {
              "type": "string"
            }
          },
          {
            "name": "to",
            "in": "query",
            "schema": {
              "type": "string"
            }
          },
          {
            "name": "date",
            "in": "query",
            "schema": {
              "type": "string",
              "format": "date-time"
            }
          }
        ],
        "responses": {
          "200": {
            "description": "OK",
            "content": {
              "text/plain": {
                "schema": {
                  "type": "array",
                  "items": {
                    "$ref": "#/components/schemas/TripDto"
                  }
                }
              },
              "application/json": {
                "schema": {
                  "type": "array",
                  "items": {
                    "$ref": "#/components/schemas/TripDto"
                  }
                }
              },
              "text/json": {
                "schema": {
                  "type": "array",
                  "items": {
                    "$ref": "#/components/schemas/TripDto"
                  }
                }
              }
            }
          }
        }
      }
    },
    "/api/Trip/filters": {
      "get": {
        "tags": [
          "Trip"
        ],
        "parameters": [
          {
            "name": "originCityName",
            "in": "query",
            "schema": {
              "type": "string"
            }
          },
          {
            "name": "destinationCityName",
            "in": "query",
            "schema": {
              "type": "string"
            }
          },
          {
            "name": "departureDate",
            "in": "query",
            "schema": {
              "type": "string",
              "format": "date-time"
            }
          },
          {
            "name": "busFeature",
            "in": "query",
            "schema": {
              "type": "string"
            }
          },
          {
            "name": "sortBy",
            "in": "query",
            "schema": {
              "type": "string"
            }
          }
        ],
        "responses": {
          "200": {
            "description": "OK",
            "content": {
              "text/plain": {
                "schema": {
                  "type": "array",
                  "items": {
                    "$ref": "#/components/schemas/TripDto"
                  }
                }
              },
              "application/json": {
                "schema": {
                  "type": "array",
                  "items": {
                    "$ref": "#/components/schemas/TripDto"
                  }
                }
              },
              "text/json": {
                "schema": {
                  "type": "array",
                  "items": {
                    "$ref": "#/components/schemas/TripDto"
                  }
                }
              }
            }
          }
        }
      }
    },
    "/api/Trip": {
      "get": {
        "tags": [
          "Trip"
        ],
        "responses": {
          "200": {
            "description": "OK",
            "content": {
              "text/plain": {
                "schema": {
                  "type": "array",
                  "items": {
                    "$ref": "#/components/schemas/TripDto"
                  }
                }
              },
              "application/json": {
                "schema": {
                  "type": "array",
                  "items": {
                    "$ref": "#/components/schemas/TripDto"
                  }
                }
              },
              "text/json": {
                "schema": {
                  "type": "array",
                  "items": {
                    "$ref": "#/components/schemas/TripDto"
                  }
                }
              }
            }
          }
        }
      },
      "post": {
        "tags": [
          "Trip"
        ],
        "requestBody": {
          "content": {
            "application/json": {
              "schema": {
                "$ref": "#/components/schemas/CreateTripDto"
              }
            },
            "text/json": {
              "schema": {
                "$ref": "#/components/schemas/CreateTripDto"
              }
            },
            "application/*+json": {
              "schema": {
                "$ref": "#/components/schemas/CreateTripDto"
              }
            }
          }
        },
        "responses": {
          "200": {
            "description": "OK"
          }
        }
      }
    },
    "/api/Trip/{id}": {
      "get": {
        "tags": [
          "Trip"
        ],
        "parameters": [
          {
            "name": "id",
            "in": "path",
            "required": true,
            "schema": {
              "type": "string",
              "format": "uuid"
            }
          }
        ],
        "responses": {
          "200": {
            "description": "OK",
            "content": {
              "text/plain": {
                "schema": {
                  "$ref": "#/components/schemas/TripDto"
                }
              },
              "application/json": {
                "schema": {
                  "$ref": "#/components/schemas/TripDto"
                }
              },
              "text/json": {
                "schema": {
                  "$ref": "#/components/schemas/TripDto"
                }
              }
            }
          }
        }
      },
      "put": {
        "tags": [
          "Trip"
        ],
        "parameters": [
          {
            "name": "id",
            "in": "path",
            "required": true,
            "schema": {
              "type": "string",
              "format": "uuid"
            }
          }
        ],
        "requestBody": {
          "content": {
            "application/json": {
              "schema": {
                "$ref": "#/components/schemas/UpdateTripDto"
              }
            },
            "text/json": {
              "schema": {
                "$ref": "#/components/schemas/UpdateTripDto"
              }
            },
            "application/*+json": {
              "schema": {
                "$ref": "#/components/schemas/UpdateTripDto"
              }
            }
          }
        },
        "responses": {
          "200": {
            "description": "OK"
          }
        }
      },
      "delete": {
        "tags": [
          "Trip"
        ],
        "parameters": [
          {
            "name": "id",
            "in": "path",
            "required": true,
            "schema": {
              "type": "string",
              "format": "uuid"
            }
          }
        ],
        "responses": {
          "200": {
            "description": "OK"
          }
        }
      }
    },
    "/api/User": {
      "get": {
        "tags": [
          "User"
        ],
        "responses": {
          "200": {
            "description": "OK",
            "content": {
              "text/plain": {
                "schema": {
                  "type": "array",
                  "items": {
                    "$ref": "#/components/schemas/UserDTOs"
                  }
                }
              },
              "application/json": {
                "schema": {
                  "type": "array",
                  "items": {
                    "$ref": "#/components/schemas/UserDTOs"
                  }
                }
              },
              "text/json": {
                "schema": {
                  "type": "array",
                  "items": {
                    "$ref": "#/components/schemas/UserDTOs"
                  }
                }
              }
            }
          }
        }
      }
    },
    "/api/User/me": {
      "get": {
        "tags": [
          "User"
        ],
        "responses": {
          "200": {
            "description": "OK",
            "content": {
              "text/plain": {
                "schema": {
                  "$ref": "#/components/schemas/UserDTOs"
                }
              },
              "application/json": {
                "schema": {
                  "$ref": "#/components/schemas/UserDTOs"
                }
              },
              "text/json": {
                "schema": {
                  "$ref": "#/components/schemas/UserDTOs"
                }
              }
            }
          }
        }
      }
    },
    "/api/User/{id}": {
      "get": {
        "tags": [
          "User"
        ],
        "parameters": [
          {
            "name": "id",
            "in": "path",
            "required": true,
            "schema": {
              "type": "string",
              "format": "uuid"
            }
          }
        ],
        "responses": {
          "200": {
            "description": "OK",
            "content": {
              "text/plain": {
                "schema": {
                  "$ref": "#/components/schemas/UserDTOs"
                }
              },
              "application/json": {
                "schema": {
                  "$ref": "#/components/schemas/UserDTOs"
                }
              },
              "text/json": {
                "schema": {
                  "$ref": "#/components/schemas/UserDTOs"
                }
              }
            }
          }
        }
      },
      "put": {
        "tags": [
          "User"
        ],
        "parameters": [
          {
            "name": "id",
            "in": "path",
            "required": true,
            "schema": {
              "type": "string",
              "format": "uuid"
            }
          }
        ],
        "requestBody": {
          "content": {
            "application/json": {
              "schema": {
                "$ref": "#/components/schemas/UpdateUserDTO"
              }
            },
            "text/json": {
              "schema": {
                "$ref": "#/components/schemas/UpdateUserDTO"
              }
            },
            "application/*+json": {
              "schema": {
                "$ref": "#/components/schemas/UpdateUserDTO"
              }
            }
          }
        },
        "responses": {
          "200": {
            "description": "OK"
          }
        }
      },
      "delete": {
        "tags": [
          "User"
        ],
        "parameters": [
          {
            "name": "id",
            "in": "path",
            "required": true,
            "schema": {
              "type": "string",
              "format": "uuid"
            }
          }
        ],
        "responses": {
          "200": {
            "description": "OK"
          }
        }
      }
    },
    "/api/User/topup": {
      "post": {
        "tags": [
          "User"
        ],
        "requestBody": {
          "content": {
            "application/json": {
              "schema": {
                "type": "number",
                "format": "double"
              }
            },
            "text/json": {
              "schema": {
                "type": "number",
                "format": "double"
              }
            },
            "application/*+json": {
              "schema": {
                "type": "number",
                "format": "double"
              }
            }
          }
        },
        "responses": {
          "200": {
            "description": "OK"
          }
        }
      }
    },
    "/api/User/register": {
      "post": {
        "tags": [
          "User"
        ],
        "requestBody": {
          "content": {
            "application/json": {
              "schema": {
                "$ref": "#/components/schemas/RegisterDto"
              }
            },
            "text/json": {
              "schema": {
                "$ref": "#/components/schemas/RegisterDto"
              }
            },
            "application/*+json": {
              "schema": {
                "$ref": "#/components/schemas/RegisterDto"
              }
            }
          }
        },
        "responses": {
          "200": {
            "description": "OK",
            "content": {
              "text/plain": {
                "schema": {
                  "$ref": "#/components/schemas/UserDTOs"
                }
              },
              "application/json": {
                "schema": {
                  "$ref": "#/components/schemas/UserDTOs"
                }
              },
              "text/json": {
                "schema": {
                  "$ref": "#/components/schemas/UserDTOs"
                }
              }
            }
          }
        }
      }
    },
    "/api/User/login": {
      "post": {
        "tags": [
          "User"
        ],
        "requestBody": {
          "content": {
            "application/json": {
              "schema": {
                "$ref": "#/components/schemas/LoginDto"
              }
            },
            "text/json": {
              "schema": {
                "$ref": "#/components/schemas/LoginDto"
              }
            },
            "application/*+json": {
              "schema": {
                "$ref": "#/components/schemas/LoginDto"
              }
            }
          }
        },
        "responses": {
          "200": {
            "description": "OK",
            "content": {
              "text/plain": {
                "schema": {
                  "$ref": "#/components/schemas/TokenResponseDto"
                }
              },
              "application/json": {
                "schema": {
                  "$ref": "#/components/schemas/TokenResponseDto"
                }
              },
              "text/json": {
                "schema": {
                  "$ref": "#/components/schemas/TokenResponseDto"
                }
              }
            }
          }
        }
      }
    },
    "/api/User/refresh-token": {
      "post": {
        "tags": [
          "User"
        ],
        "requestBody": {
          "content": {
            "application/json": {
              "schema": {
                "$ref": "#/components/schemas/RefreshTokenDto"
              }
            },
            "text/json": {
              "schema": {
                "$ref": "#/components/schemas/RefreshTokenDto"
              }
            },
            "application/*+json": {
              "schema": {
                "$ref": "#/components/schemas/RefreshTokenDto"
              }
            }
          }
        },
        "responses": {
          "200": {
            "description": "OK",
            "content": {
              "text/plain": {
                "schema": {
                  "$ref": "#/components/schemas/TokenResponseDto"
                }
              },
              "application/json": {
                "schema": {
                  "$ref": "#/components/schemas/TokenResponseDto"
                }
              },
              "text/json": {
                "schema": {
                  "$ref": "#/components/schemas/TokenResponseDto"
                }
              }
            }
          }
        }
      }
    },
    "/api/User/change-password": {
      "post": {
        "tags": [
          "User"
        ],
        "requestBody": {
          "content": {
            "application/json": {
              "schema": {
                "$ref": "#/components/schemas/ChangePasswordDto"
              }
            },
            "text/json": {
              "schema": {
                "$ref": "#/components/schemas/ChangePasswordDto"
              }
            },
            "application/*+json": {
              "schema": {
                "$ref": "#/components/schemas/ChangePasswordDto"
              }
            }
          }
        },
        "responses": {
          "200": {
            "description": "OK"
          }
        }
      }
    },
    "/api/User/{id}/reset-password": {
      "post": {
        "tags": [
          "User"
        ],
        "parameters": [
          {
            "name": "id",
            "in": "path",
            "required": true,
            "schema": {
              "type": "string",
              "format": "uuid"
            }
          }
        ],
        "requestBody": {
          "content": {
            "application/json": {
              "schema": {
                "$ref": "#/components/schemas/AdminResetPasswordDto"
              }
            },
            "text/json": {
              "schema": {
                "$ref": "#/components/schemas/AdminResetPasswordDto"
              }
            },
            "application/*+json": {
              "schema": {
                "$ref": "#/components/schemas/AdminResetPasswordDto"
              }
            }
          }
        },
        "responses": {
          "200": {
            "description": "OK"
          }
        }
      }
    }
  },
  "components": {
    "schemas": {
      "AdminResetPasswordDto": {
        "type": "object",
        "properties": {
          "newPassword": {
            "type": "string",
            "nullable": true
          }
        },
        "additionalProperties": false
      },
      "BookingDto": {
        "type": "object",
        "properties": {
          "bookingId": {
            "type": "string",
            "format": "uuid"
          },
          "userId": {
            "type": "string",
            "format": "uuid"
          },
          "tripId": {
            "type": "string",
            "format": "uuid"
          },
          "originName": {
            "type": "string",
            "nullable": true
          },
          "destinationName": {
            "type": "string",
            "nullable": true
          },
          "busType": {
            "type": "string",
            "nullable": true
          },
          "bookingDate": {
            "type": "string",
            "format": "date-time"
          },
          "bookingStatus": {
            "type": "string",
            "nullable": true
          },
          "priceTotal": {
            "type": "number",
            "format": "double"
          },
          "quantity": {
            "type": "integer",
            "format": "int32"
          }
        },
        "additionalProperties": false
      },
      "BusDto": {
        "type": "object",
        "properties": {
          "busId": {
            "type": "string",
            "format": "uuid"
          },
          "operator": {
            "type": "string",
            "nullable": true
          },
          "type": {
            "type": "string",
            "nullable": true
          },
          "capacity": {
            "type": "integer",
            "format": "int32"
          },
          "model": {
            "type": "string",
            "nullable": true
          },
          "modelYear": {
            "type": "integer",
            "format": "int32"
          },
          "driverName": {
            "type": "string",
            "nullable": true
          },
          "features": {
            "type": "string",
            "nullable": true
          }
        },
        "additionalProperties": false
      },
      "ChangePasswordDto": {
        "type": "object",
        "properties": {
          "oldPassword": {
            "type": "string",
            "nullable": true
          },
          "newPassword": {
            "type": "string",
            "nullable": true
          }
        },
        "additionalProperties": false
      },
      "CityDto": {
        "type": "object",
        "properties": {
          "id": {
            "type": "string",
            "nullable": true
          },
          "nameEn": {
            "type": "string",
            "nullable": true
          },
          "nameAr": {
            "type": "string",
            "nullable": true
          },
          "busStations": {
            "type": "array",
            "items": {
              "$ref": "#/components/schemas/StationDto"
            },
            "nullable": true
          }
        },
        "additionalProperties": false
      },
      "CreateBookingDto": {
        "required": [
          "tripId",
          "userId"
        ],
        "type": "object",
        "properties": {
          "userId": {
            "type": "string",
            "format": "uuid"
          },
          "tripId": {
            "type": "string",
            "format": "uuid"
          },
          "bookingDate": {
            "type": "string",
            "format": "date-time"
          },
          "bookingStatus": {
            "type": "string",
            "nullable": true
          },
          "quantity": {
            "maximum": 10,
            "minimum": 1,
            "type": "integer",
            "format": "int32"
          }
        },
        "additionalProperties": false
      },
      "CreateBusDto": {
        "required": [
          "operator",
          "type"
        ],
        "type": "object",
        "properties": {
          "operator": {
            "minLength": 1,
            "type": "string"
          },
          "type": {
            "minLength": 1,
            "type": "string"
          },
          "capacity": {
            "maximum": 50,
            "minimum": 1,
            "type": "integer",
            "format": "int32"
          },
          "model": {
            "type": "string",
            "nullable": true
          },
          "modelYear": {
            "type": "integer",
            "format": "int32"
          },
          "driverName": {
            "type": "string",
            "nullable": true
          },
          "features": {
            "type": "string",
            "nullable": true
          }
        },
        "additionalProperties": false
      },
      "CreateStationDto": {
        "type": "object",
        "properties": {
          "cityId": {
            "type": "string",
            "nullable": true
          },
          "nameEn": {
            "type": "string",
            "nullable": true
          },
          "stationName": {
            "type": "string",
            "nullable": true
          },
          "streetEn": {
            "type": "string",
            "nullable": true
          },
          "lat": {
            "type": "number",
            "format": "double",
            "nullable": true
          },
          "lng": {
            "type": "number",
            "format": "double",
            "nullable": true
          }
        },
        "additionalProperties": false
      },
      "CreateTripDto": {
        "required": [
          "availableSeats",
          "busId",
          "departureDate",
          "departureTime",
          "destinationStationId",
          "originStationId",
          "priceJod",
          "routeId"
        ],
        "type": "object",
        "properties": {
          "routeId": {
            "type": "string",
            "format": "uuid"
          },
          "busId": {
            "type": "string",
            "format": "uuid"
          },
          "originStationId": {
            "type": "string",
            "format": "uuid"
          },
          "destinationStationId": {
            "type": "string",
            "format": "uuid"
          },
          "departureDate": {
            "type": "string",
            "format": "date"
          },
          "departureTime": {
            "type": "string",
            "format": "time"
          },
          "availableSeats": {
            "type": "integer",
            "format": "int32"
          },
          "priceJod": {
            "type": "number",
            "format": "double"
          },
          "status": {
            "type": "string",
            "nullable": true
          }
        },
        "additionalProperties": false
      },
      "LoginDto": {
        "type": "object",
        "properties": {
          "username": {
            "type": "string",
            "nullable": true
          },
          "password": {
            "type": "string",
            "nullable": true
          }
        },
        "additionalProperties": false
      },
      "RefreshTokenDto": {
        "type": "object",
        "properties": {
          "userId": {
            "type": "string",
            "format": "uuid"
          },
          "refreshToken": {
            "type": "string",
            "nullable": true
          }
        },
        "additionalProperties": false
      },
      "RegisterDto": {
        "type": "object",
        "properties": {
          "username": {
            "type": "string",
            "nullable": true
          },
          "fullName": {
            "type": "string",
            "nullable": true
          },
          "email": {
            "type": "string",
            "nullable": true
          },
          "password": {
            "type": "string",
            "nullable": true
          },
          "phone": {
            "type": "string",
            "nullable": true
          }
        },
        "additionalProperties": false
      },
      "RouteDto": {
        "type": "object",
        "properties": {
          "routeId": {
            "type": "string",
            "format": "uuid"
          },
          "originId": {
            "type": "string",
            "nullable": true
          },
          "destinationId": {
            "type": "string",
            "nullable": true
          },
          "distanceKm": {
            "type": "integer",
            "format": "int32"
          },
          "durationHrs": {
            "type": "number",
            "format": "double"
          }
        },
        "additionalProperties": false
      },
      "StationDto": {
        "type": "object",
        "properties": {
          "id": {
            "type": "string",
            "format": "uuid"
          },
          "nameEn": {
            "type": "string",
            "nullable": true
          },
          "stationName": {
            "type": "string",
            "nullable": true
          },
          "streetEn": {
            "type": "string",
            "nullable": true
          },
          "lat": {
            "type": "number",
            "format": "double",
            "nullable": true
          },
          "lng": {
            "type": "number",
            "format": "double",
            "nullable": true
          }
        },
        "additionalProperties": false
      },
      "TokenResponseDto": {
        "type": "object",
        "properties": {
          "accessToken": {
            "type": "string",
            "nullable": true
          },
          "refreshToken": {
            "type": "string",
            "nullable": true
          }
        },
        "additionalProperties": false
      },
      "TripDto": {
        "type": "object",
        "properties": {
          "tripId": {
            "type": "string",
            "format": "uuid"
          },
          "routeId": {
            "type": "string",
            "format": "uuid"
          },
          "busId": {
            "type": "string",
            "format": "uuid"
          },
          "departureDate": {
            "type": "string",
            "format": "date"
          },
          "departureTime": {
            "type": "string",
            "format": "time"
          },
          "availableSeats": {
            "type": "integer",
            "format": "int32"
          },
          "priceJod": {
            "type": "number",
            "format": "double"
          },
          "status": {
            "type": "string",
            "nullable": true
          },
          "originName": {
            "type": "string",
            "nullable": true
          },
          "destinationName": {
            "type": "string",
            "nullable": true
          },
          "busType": {
            "type": "string",
            "nullable": true
          },
          "driverName": {
            "type": "string",
            "nullable": true
          },
          "features": {
            "type": "string",
            "nullable": true
          },
          "originStationId": {
            "type": "string",
            "format": "uuid"
          },
          "originStationName": {
            "type": "string",
            "nullable": true
          },
          "originStationNameEn": {
            "type": "string",
            "nullable": true
          },
          "originStationStreet": {
            "type": "string",
            "nullable": true
          },
          "originStationLat": {
            "type": "number",
            "format": "double",
            "nullable": true
          },
          "originStationLng": {
            "type": "number",
            "format": "double",
            "nullable": true
          },
          "destinationStationId": {
            "type": "string",
            "format": "uuid"
          },
          "destinationStationName": {
            "type": "string",
            "nullable": true
          },
          "destinationStationNameEn": {
            "type": "string",
            "nullable": true
          },
          "destinationStationStreet": {
            "type": "string",
            "nullable": true
          },
          "destinationStationLat": {
            "type": "number",
            "format": "double",
            "nullable": true
          },
          "destinationStationLng": {
            "type": "number",
            "format": "double",
            "nullable": true
          }
        },
        "additionalProperties": false
      },
      "UpdateBusDto": {
        "type": "object",
        "properties": {
          "operator": {
            "type": "string",
            "nullable": true
          },
          "type": {
            "type": "string",
            "nullable": true
          },
          "capacity": {
            "type": "integer",
            "format": "int32"
          },
          "model": {
            "type": "string",
            "nullable": true
          },
          "modelYear": {
            "type": "integer",
            "format": "int32"
          },
          "driverName": {
            "type": "string",
            "nullable": true
          },
          "features": {
            "type": "string",
            "nullable": true
          }
        },
        "additionalProperties": false
      },
      "UpdateStationDto": {
        "type": "object",
        "properties": {
          "nameEn": {
            "type": "string",
            "nullable": true
          },
          "stationName": {
            "type": "string",
            "nullable": true
          },
          "streetEn": {
            "type": "string",
            "nullable": true
          },
          "lat": {
            "type": "number",
            "format": "double",
            "nullable": true
          },
          "lng": {
            "type": "number",
            "format": "double",
            "nullable": true
          }
        },
        "additionalProperties": false
      },
      "UpdateTripDto": {
        "type": "object",
        "properties": {
          "routeId": {
            "type": "string",
            "format": "uuid"
          },
          "busId": {
            "type": "string",
            "format": "uuid"
          },
          "originStationId": {
            "type": "string",
            "format": "uuid"
          },
          "destinationStationId": {
            "type": "string",
            "format": "uuid"
          },
          "departureDate": {
            "type": "string",
            "format": "date"
          },
          "departureTime": {
            "type": "string",
            "format": "time"
          },
          "availableSeats": {
            "type": "integer",
            "format": "int32"
          },
          "priceJod": {
            "type": "number",
            "format": "double"
          },
          "status": {
            "type": "string",
            "nullable": true
          }
        },
        "additionalProperties": false
      },
      "UpdateUserDTO": {
        "type": "object",
        "properties": {
          "fullName": {
            "type": "string",
            "nullable": true
          },
          "email": {
            "type": "string",
            "nullable": true
          },
          "phone": {
            "type": "string",
            "nullable": true
          }
        },
        "additionalProperties": false
      },
      "UserDTOs": {
        "type": "object",
        "properties": {
          "userId": {
            "type": "string",
            "format": "uuid"
          },
          "username": {
            "type": "string",
            "nullable": true
          },
          "fullName": {
            "type": "string",
            "nullable": true
          },
          "email": {
            "type": "string",
            "nullable": true
          },
          "phone": {
            "type": "string",
            "nullable": true
          },
          "role": {
            "type": "string",
            "nullable": true
          },
          "balance": {
            "type": "number",
            "format": "double"
          }
        },
        "additionalProperties": false
      }
    },
    "securitySchemes": {
      "Bearer": {
        "type": "http",
        "description": "Enter: Bearer {your JWT token}",
        "scheme": "Bearer",
        "bearerFormat": "JWT"
      }
    }
  },
  "security": [
    {
      "Bearer": [ ]
    }
  ]
}